{
    "Boards": [
        {
            "ID": "0x01",
            "Name": "PiBox"
        },
        {
            "ID": "0x02",
            "Name": "Steering wheel"
        },
        {
            "ID": "0x10",
            "Name": "Battery 1"
        },
        {
            "ID": "0x11",
            "Name": "Battery 2"
        }
    ],
    "Parameters": [
        {
            "ID": "0x0001",
            "Name": "Heartbeat", 
            "Type": "uint32"
        },
        {
            "MinID": "0x0010",
            "MaxID": "0x004F",
            "Name": "Binary channel <x>", 
            "Type": "bool"
        },
        {
            "MinID": "0x0050",
            "MaxID": "0x008F",
            "Name": "Voltage channel <x>", 
            "Type": "float"
        },
        {
            "MinID": "0x0090",
            "MaxID": "207",
            "Name": "Current channel <x>", 
            "Type": "float"
        },
        {
            "ID": "0x0100",
            "Name": "Latitude",
            "Type": "float"
        },
        {
            "ID": "0x0101",
            "Name": "Longitude",
            "Type": "float"
        },
        {
            "ID": "0x0102",
            "Name": "Altitude",
            "Type": "float"
        }
    ]
}